.editorconfig
.gitignore
.gitlab-ci.yml
.gitmodules
CITATION.cff
LICENSE
MANIFEST.in
Makefile.in
README.rst
README_SETUP.txt
aksetup_helper.py
configure.py
pyproject.toml
setup.cfg
setup.py
.github/ISSUE_TEMPLATE/bug_report.md
.github/ISSUE_TEMPLATE/config.yml
.github/ISSUE_TEMPLATE/feature_request.md
.github/workflows/autopush.yml
.github/workflows/ci.yml
bpl-subset/bpl_subset/boost/aligned_storage.hpp
bpl-subset/bpl_subset/boost/array.hpp
bpl-subset/bpl_subset/boost/assert.hpp
bpl-subset/bpl_subset/boost/bind.hpp
bpl-subset/bpl_subset/boost/call_traits.hpp
bpl-subset/bpl_subset/boost/cast.hpp
bpl-subset/bpl_subset/boost/cerrno.hpp
bpl-subset/bpl_subset/boost/checked_delete.hpp
bpl-subset/bpl_subset/boost/circular_buffer.hpp
bpl-subset/bpl_subset/boost/circular_buffer_fwd.hpp
bpl-subset/bpl_subset/boost/compressed_pair.hpp
bpl-subset/bpl_subset/boost/concept_archetype.hpp
bpl-subset/bpl_subset/boost/concept_check.hpp
bpl-subset/bpl_subset/boost/config.hpp
bpl-subset/bpl_subset/boost/cstdint.hpp
bpl-subset/bpl_subset/boost/cstdlib.hpp
bpl-subset/bpl_subset/boost/current_function.hpp
bpl-subset/bpl_subset/boost/date_time.hpp
bpl-subset/bpl_subset/boost/dynamic_bitset.hpp
bpl-subset/bpl_subset/boost/dynamic_bitset_fwd.hpp
bpl-subset/bpl_subset/boost/enable_shared_from_this.hpp
bpl-subset/bpl_subset/boost/exception_ptr.hpp
bpl-subset/bpl_subset/boost/foreach.hpp
bpl-subset/bpl_subset/boost/foreach_fwd.hpp
bpl-subset/bpl_subset/boost/format.hpp
bpl-subset/bpl_subset/boost/function.hpp
bpl-subset/bpl_subset/boost/function_equal.hpp
bpl-subset/bpl_subset/boost/get_pointer.hpp
bpl-subset/bpl_subset/boost/implicit_cast.hpp
bpl-subset/bpl_subset/boost/indirect_reference.hpp
bpl-subset/bpl_subset/boost/integer.hpp
bpl-subset/bpl_subset/boost/integer_fwd.hpp
bpl-subset/bpl_subset/boost/integer_traits.hpp
bpl-subset/bpl_subset/boost/intrusive_ptr.hpp
bpl-subset/bpl_subset/boost/io_fwd.hpp
bpl-subset/bpl_subset/boost/is_placeholder.hpp
bpl-subset/bpl_subset/boost/iterator.hpp
pycuda.egg-info/PKG-INFO
pycuda.egg-info/SOURCES.txt
pycuda.egg-info/dependency_links.txt
pycuda.egg-info/not-zip-safe
pycuda.egg-info/requires.txt
pycuda.egg-info/top_level.txt
